mldrive/__init__.py
mldrive/mldrive.py
mldrive-1.1.2.dist-info/METADATA
mldrive-1.1.2.dist-info/WHEEL
mldrive-1.1.2.dist-info/top_level.txt
mldrive-1.1.2.dist-info/RECORD
